deribit_api.py
deribit_api-1.1.0.dist-info/top_level.txt
deribit_api-1.1.0.dist-info/METADATA
deribit_api-1.1.0.dist-info/DESCRIPTION.rst
deribit_api-1.1.0.dist-info/metadata.json
deribit_api-1.1.0.dist-info/WHEEL
deribit_api-1.1.0.dist-info/RECORD
