Metadata-Version: 2.0
Name: deribit-api
Version: 1.1.0
Summary: API Client for Deribit API
Home-page: https://github.com/deribit/deribit-api-python
Author: Deribit
Author-email: contact@deribit.com
License: MIT
Keywords: deribit api
Platform: UNKNOWN
Classifier: Development Status :: 5 - Production/Stable
Classifier: Intended Audience :: Developers
Classifier: License :: OSI Approved :: MIT License
Classifier: Programming Language :: Python :: 2
Classifier: Programming Language :: Python :: 2.7
Classifier: Programming Language :: Python :: 3
Classifier: Programming Language :: Python :: 3.3
Classifier: Programming Language :: Python :: 3.4
Classifier: Programming Language :: Python :: 3.5
Requires-Dist: requests
